arctable_toolkit/BaseProcessor.py
arctable_toolkit/DataCatalog.py
arctable_toolkit/ExtendedDataCatalog.py
arctable_toolkit/TableLoader.py
arctable_toolkit/__init__.py
ArcTableToolkit-0.6.0.dist-info/METADATA
ArcTableToolkit-0.6.0.dist-info/WHEEL
ArcTableToolkit-0.6.0.dist-info/top_level.txt
ArcTableToolkit-0.6.0.dist-info/RECORD
