Metadata-Version: 2.1
Name: ArcTableToolkit
Version: 0.6.0
Summary: Short description of your package
Home-page: https://github.com/yourusername/your-package
Author: Joel G. Castro
Author-email: CastroJG@elpasotexas.gov
Classifier: Programming Language :: Python :: 3
Classifier: License :: OSI Approved :: MIT License
Classifier: Operating System :: OS Independent
Requires-Dist: numpy
Requires-Dist: scipy
